LICENSE
README.md
antyr/__init__.py
antyr/constants.py
antyr/crawlers.py
antyr/execution.py
antyr/files.py
antyr/func.py
antyr/results.py
antyr/streaming.py
antyr/zip.py
antyr-1.0.1.dist-info/METADATA
antyr-1.0.1.dist-info/WHEEL
antyr-1.0.1.dist-info/licenses/LICENSE
antyr-1.0.1.dist-info/RECORD
