Metadata-Version: 2.4
Name: antyr
Version: 1.0.1
Summary: The compact web crawling toolkit
Project-URL: Homepage, https://github.com/mrprfrm/antyr
Author-email: Anton Petrov <mrprfrm@gmail.com>
License-File: LICENSE
Classifier: Intended Audience :: Developers
Classifier: Programming Language :: Python :: 3
Classifier: Topic :: Internet :: WWW/HTTP
Classifier: Typing :: Typed
Requires-Python: >=3.11
Requires-Dist: httpx[socks]>=0.28.1
Requires-Dist: stem>=1.8.2
Requires-Dist: trio>=0.32.0
